AUTHORS.rst
CONTRIBUTING.rst
HISTORY.rst
LICENSE
MANIFEST.in
README.md
requirements.txt
setup.cfg
setup.py
docs/Makefile
docs/authors.rst
docs/conf.py
docs/contributing.rst
docs/history.rst
docs/index.rst
docs/installation.rst
docs/make.bat
docs/modules.rst
docs/readme.rst
docs/storage_provisioner.rst
docs/usage.rst
storage_provisioner/__init__.py
storage_provisioner/provisioner.py
storage_provisioner/storage.py
storage_provisioner.egg-info/PKG-INFO
storage_provisioner.egg-info/SOURCES.txt
storage_provisioner.egg-info/dependency_links.txt
storage_provisioner.egg-info/not-zip-safe
storage_provisioner.egg-info/pbr.json
storage_provisioner.egg-info/requires.txt
storage_provisioner.egg-info/top_level.txt
tests/__init__.py
tests/secrets.py
tests/test_provisioner.py
tests/test_storage.py