Metadata-Version: 1.1
Name: storage-provisioner
Version: 0.1.2
Summary: Provisions storage on pluggable backends, such as AWS S3.
Home-page: https://github.com/PerchLive/storage_provisioner
Author: Chris Ballinger, David Brodsky
Author-email: chrisballinger@gmail.com, dbro@dbro.pro
License: Apache License 2.0
Download-URL: https://github.com/PerchLive/storage_provisioner/tarball/0.1.2
Keywords: storage_provisioner,aws,boto
Platform: UNKNOWN
Classifier: Development Status :: 2 - Pre-Alpha
Classifier: Intended Audience :: Developers
Classifier: License :: OSI Approved :: Apache Software License
Classifier: Natural Language :: English
Classifier: Programming Language :: Python :: 2.7
Classifier: Programming Language :: Python :: 3.5
